SeanFunctions/__init__.py
SeanFunctions/fitting.py
SeanFunctions/math.py
SeanFunctions/scattering.py
SeanFunctions/Data/AtomicFormFactorConstants.csv
SeanFunctions/Data/NeutronScatteringLengths.csv
SeanFunctions/Data/NeutronScatteringLengths_Corrected.csv
SeanFunctions-0.5.7.dist-info/LICENSE
SeanFunctions-0.5.7.dist-info/METADATA
SeanFunctions-0.5.7.dist-info/WHEEL
SeanFunctions-0.5.7.dist-info/top_level.txt
SeanFunctions-0.5.7.dist-info/RECORD
