Metadata-Version: 2.1
Name: SeanFunctions
Version: 0.5.7
Summary: Collection of useful python functions
Author-email: Sean Fayfar <sfayfar@gmail.com>
Project-URL: Homepage, https://github.com/sfayfar/SeanFunctions
Project-URL: Bug Tracker, https://github.com/sfayfar/SeanFunctions/issues
Classifier: Programming Language :: Python :: 3
Classifier: License :: OSI Approved :: MIT License
Classifier: Operating System :: OS Independent
Requires-Python: >=3.7
License-File: LICENSE
Requires-Dist: numpy
Requires-Dist: scipy
Requires-Dist: lmfit
Requires-Dist: uncertainties
Requires-Dist: mendeleev
